{
    "signal_type": "DWT",
    "metrics": [
        {
            "metric": "emd_value",
            "original_weight": 0.3,
            "normalized_weight": null,
            "was_normalized": true,
            "was_inverted": false,
            "was_shared": false,
            "was_specific": false,
            "max_value": null,
            "min_value": null,
            "std_dev": null,
            "mean": null,
            "variance": null,
            "presence": null,
            "ignore_metric": false,
            "removal_reason": null,
            "was_log_transformed": false,
            "low_variance_detected": false,
            "across_mean": 0.007890188205922072,
            "across_std": 0.08150022616225461,
            "across_max": 0.9508133760647561,
            "across_min": 2.1190281796294868e-14,
            "mean_normalized": 0.00829835633839851,
            "std_normalized": 0.08571632269160016,
            "max_normalized": 1.0,
            "min_normalized": 0.0
        },
        {
            "metric": "smoothness",
            "original_weight": 0.3,
            "normalized_weight": null,
            "was_normalized": true,
            "was_inverted": false,
            "was_shared": false,
            "was_specific": false,
            "max_value": null,
            "min_value": null,
            "std_dev": null,
            "mean": null,
            "variance": null,
            "presence": null,
            "ignore_metric": false,
            "removal_reason": null,
            "was_log_transformed": false,
            "low_variance_detected": false,
            "across_mean": 4.9218504755063805e-05,
            "across_std": 4.64047316047439e-05,
            "across_max": 9.561500518422448e-05,
            "across_min": 2.8144846061549238e-06,
            "mean_normalized": 0.5000405155041229,
            "std_normalized": 0.5000481820110628,
            "max_normalized": 1.0,
            "min_normalized": 0.0
        },
        {
            "metric": "wavelet_mse",
            "original_weight": 0.6,
            "normalized_weight": null,
            "was_normalized": true,
            "was_inverted": false,
            "was_shared": false,
            "was_specific": false,
            "max_value": null,
            "min_value": null,
            "std_dev": null,
            "mean": null,
            "variance": null,
            "presence": null,
            "ignore_metric": false,
            "removal_reason": null,
            "was_log_transformed": false,
            "low_variance_detected": false,
            "across_mean": 0.010111949785693141,
            "across_std": 0.10797591231464146,
            "across_max": 1.4000919935891412,
            "across_min": 2.389215014345788e-27,
            "mean_normalized": 0.0072223466972131745,
            "std_normalized": 0.07712058408236788,
            "max_normalized": 1.0,
            "min_normalized": 0.0
        },
        {
            "metric": "wavelet_psnr",
            "original_weight": 0.6,
            "normalized_weight": null,
            "was_normalized": true,
            "was_inverted": false,
            "was_shared": false,
            "was_specific": false,
            "max_value": null,
            "min_value": null,
            "std_dev": null,
            "mean": null,
            "variance": null,
            "presence": null,
            "ignore_metric": false,
            "removal_reason": null,
            "was_log_transformed": false,
            "low_variance_detected": false,
            "across_mean": 305.4295294640623,
            "across_std": 34.8937335842348,
            "across_max": 330.15754220761687,
            "across_min": 62.4785288394245,
            "mean_normalized": 0.9076206519427762,
            "std_normalized": 0.13035662805674825,
            "max_normalized": 1.0,
            "min_normalized": 0.0
        },
        {
            "metric": "wavelet_entropy",
            "original_weight": 0.5,
            "normalized_weight": null,
            "was_normalized": true,
            "was_inverted": false,
            "was_shared": false,
            "was_specific": false,
            "max_value": null,
            "min_value": null,
            "std_dev": null,
            "mean": null,
            "variance": null,
            "presence": null,
            "ignore_metric": false,
            "removal_reason": null,
            "was_log_transformed": false,
            "low_variance_detected": false,
            "across_mean": 8.04506742723629,
            "across_std": 0.11086125759932995,
            "across_max": 8.43556629744622,
            "across_min": 7.724159381629948,
            "mean_normalized": 0.4510892970981741,
            "std_normalized": 0.15583382046845468,
            "max_normalized": 1.0,
            "min_normalized": 0.0
        },
        {
            "metric": "wavelet_energy_entropy",
            "original_weight": 0.5,
            "normalized_weight": null,
            "was_normalized": true,
            "was_inverted": false,
            "was_shared": false,
            "was_specific": false,
            "max_value": null,
            "min_value": null,
            "std_dev": null,
            "mean": null,
            "variance": null,
            "presence": null,
            "ignore_metric": false,
            "removal_reason": null,
            "was_log_transformed": false,
            "low_variance_detected": false,
            "across_mean": 29677774.855712734,
            "across_std": 3205493.5794447083,
            "across_max": 41251881.89423117,
            "across_min": 25695404.727448594,
            "mean_normalized": 0.2559943414931765,
            "std_normalized": 0.2060552363544963,
            "max_normalized": 1.0,
            "min_normalized": 0.0
        },
        {
            "metric": "wavelet_sparsity",
            "original_weight": 0.4,
            "normalized_weight": null,
            "was_normalized": true,
            "was_inverted": false,
            "was_shared": false,
            "was_specific": false,
            "max_value": null,
            "min_value": null,
            "std_dev": null,
            "mean": null,
            "variance": null,
            "presence": null,
            "ignore_metric": false,
            "removal_reason": null,
            "was_log_transformed": false,
            "low_variance_detected": false,
            "across_mean": 0.5804442052536498,
            "across_std": 0.031198366695045065,
            "across_max": 0.6478494623655914,
            "across_min": 0.5375,
            "mean_normalized": 0.3891655141134655,
            "std_normalized": 0.2827233230342695,
            "max_normalized": 1.0,
            "min_normalized": 0.0
        },
        {
            "metric": "correlation",
            "original_weight": 0.4,
            "normalized_weight": null,
            "was_normalized": false,
            "was_inverted": false,
            "was_shared": false,
            "was_specific": false,
            "max_value": null,
            "min_value": null,
            "std_dev": null,
            "mean": null,
            "variance": null,
            "presence": null,
            "ignore_metric": true,
            "removal_reason": "Low variance (std: 0.000000, mean: 1.000000)",
            "was_log_transformed": false,
            "low_variance_detected": true,
            "across_mean": 0.9999999871205475,
            "across_std": 1.356916778451472e-07,
            "across_max": 1.0,
            "across_min": 0.9999982229877716
        },
        {
            "metric": "avg_variance_across_levels",
            "original_weight": 0.4,
            "normalized_weight": null,
            "was_normalized": true,
            "was_inverted": false,
            "was_shared": false,
            "was_specific": false,
            "max_value": null,
            "min_value": null,
            "std_dev": null,
            "mean": null,
            "variance": null,
            "presence": null,
            "ignore_metric": false,
            "removal_reason": null,
            "was_log_transformed": false,
            "low_variance_detected": false,
            "across_mean": 109523.76222184408,
            "across_std": 36391.586374637554,
            "across_max": 234988.4295555624,
            "across_min": 63728.99780417078,
            "mean_normalized": 0.2673999554322425,
            "std_normalized": 0.21249391056876396,
            "max_normalized": 1.0,
            "min_normalized": 0.0
        },
        {
            "metric": "kl_divergence",
            "original_weight": 0.4,
            "normalized_weight": null,
            "was_normalized": false,
            "was_inverted": false,
            "was_shared": false,
            "was_specific": false,
            "max_value": null,
            "min_value": null,
            "std_dev": null,
            "mean": null,
            "variance": null,
            "presence": null,
            "ignore_metric": true,
            "removal_reason": "Low variance (std: 0.000000, mean: -0.000000)",
            "was_log_transformed": false,
            "low_variance_detected": true,
            "across_mean": -5.169498390354825e-10,
            "across_std": 1.8022542363479425e-09,
            "across_max": 2.322566929057822e-08,
            "across_min": -8.342966320149071e-10
        },
        {
            "metric": "prominence_min_diff",
            "original_weight": 0.3,
            "normalized_weight": null,
            "was_normalized": true,
            "was_inverted": false,
            "was_shared": false,
            "was_specific": false,
            "max_value": null,
            "min_value": null,
            "std_dev": null,
            "mean": null,
            "variance": null,
            "presence": null,
            "ignore_metric": false,
            "removal_reason": null,
            "was_log_transformed": false,
            "low_variance_detected": false,
            "across_mean": 413.91849213422097,
            "across_std": 241.96991156875933,
            "across_max": 658.4397130192756,
            "across_min": 171.99999999422346,
            "mean_normalized": 0.4973247160178686,
            "std_normalized": 0.49743042167344104,
            "max_normalized": 1.0000000000000002,
            "min_normalized": 0.0
        },
        {
            "metric": "positive_amplitudes_dtw",
            "original_weight": 0.35,
            "normalized_weight": null,
            "was_normalized": false,
            "was_inverted": false,
            "was_shared": false,
            "was_specific": false,
            "max_value": null,
            "min_value": null,
            "std_dev": null,
            "mean": null,
            "variance": null,
            "presence": null,
            "ignore_metric": false,
            "removal_reason": null,
            "was_log_transformed": false,
            "low_variance_detected": false
        },
        {
            "metric": "positive_amplitudes_euclidean",
            "original_weight": 0.35,
            "normalized_weight": null,
            "was_normalized": false,
            "was_inverted": false,
            "was_shared": false,
            "was_specific": false,
            "max_value": null,
            "min_value": null,
            "std_dev": null,
            "mean": null,
            "variance": null,
            "presence": null,
            "ignore_metric": false,
            "removal_reason": null,
            "was_log_transformed": false,
            "low_variance_detected": false
        },
        {
            "metric": "positive_amplitudes_wasserstein",
            "original_weight": 0.35,
            "normalized_weight": null,
            "was_normalized": false,
            "was_inverted": false,
            "was_shared": false,
            "was_specific": false,
            "max_value": null,
            "min_value": null,
            "std_dev": null,
            "mean": null,
            "variance": null,
            "presence": null,
            "ignore_metric": false,
            "removal_reason": null,
            "was_log_transformed": false,
            "low_variance_detected": false
        },
        {
            "metric": "avg_prominence_diff",
            "original_weight": 0.3,
            "normalized_weight": null,
            "was_normalized": true,
            "was_inverted": false,
            "was_shared": false,
            "was_specific": false,
            "max_value": null,
            "min_value": null,
            "std_dev": null,
            "mean": null,
            "variance": null,
            "presence": null,
            "ignore_metric": false,
            "removal_reason": null,
            "was_log_transformed": false,
            "low_variance_detected": false,
            "across_mean": 534.4993596323959,
            "across_std": 59.625758881480905,
            "across_max": 596.5600909965777,
            "across_min": 474.86204619206194,
            "mean_normalized": 0.4900433161118544,
            "std_normalized": 0.48994837162140165,
            "max_normalized": 0.9999999999999999,
            "min_normalized": 0.0
        },
        {
            "metric": "relative_prominences_avg_diff",
            "original_weight": 0.3,
            "normalized_weight": null,
            "was_normalized": true,
            "was_inverted": false,
            "was_shared": false,
            "was_specific": false,
            "max_value": null,
            "min_value": null,
            "std_dev": null,
            "mean": null,
            "variance": null,
            "presence": null,
            "ignore_metric": false,
            "removal_reason": null,
            "was_log_transformed": false,
            "low_variance_detected": false,
            "across_mean": 534.4993596323959,
            "across_std": 59.625758881480905,
            "across_max": 596.5600909965777,
            "across_min": 474.86204619206194,
            "mean_normalized": 0.4900433161118544,
            "std_normalized": 0.48994837162140165,
            "max_normalized": 0.9999999999999999,
            "min_normalized": 0.0
        },
        {
            "metric": "relative_prominences_wasserstein",
            "original_weight": 0.3,
            "normalized_weight": null,
            "was_normalized": true,
            "was_inverted": false,
            "was_shared": false,
            "was_specific": false,
            "max_value": null,
            "min_value": null,
            "std_dev": null,
            "mean": null,
            "variance": null,
            "presence": null,
            "ignore_metric": false,
            "removal_reason": null,
            "was_log_transformed": false,
            "low_variance_detected": false,
            "across_mean": 534.4993596323993,
            "across_std": 59.62575888147977,
            "across_max": 596.5600909965777,
            "across_min": 474.86204619240624,
            "mean_normalized": 0.4900433161104399,
            "std_normalized": 0.4899483716227786,
            "max_normalized": 1.0,
            "min_normalized": 0.0
        },
        {
            "metric": "positive_frequencies_dtw",
            "original_weight": 0.35,
            "normalized_weight": null,
            "was_normalized": false,
            "was_inverted": false,
            "was_shared": false,
            "was_specific": false,
            "max_value": null,
            "min_value": null,
            "std_dev": null,
            "mean": null,
            "variance": null,
            "presence": null,
            "ignore_metric": false,
            "removal_reason": null,
            "was_log_transformed": false,
            "low_variance_detected": false
        },
        {
            "metric": "positive_frequencies_euclidean",
            "original_weight": 0.35,
            "normalized_weight": null,
            "was_normalized": false,
            "was_inverted": false,
            "was_shared": false,
            "was_specific": false,
            "max_value": null,
            "min_value": null,
            "std_dev": null,
            "mean": null,
            "variance": null,
            "presence": null,
            "ignore_metric": false,
            "removal_reason": null,
            "was_log_transformed": false,
            "low_variance_detected": false
        },
        {
            "metric": "positive_frequencies_wasserstein",
            "original_weight": 0.35,
            "normalized_weight": null,
            "was_normalized": false,
            "was_inverted": false,
            "was_shared": false,
            "was_specific": false,
            "max_value": null,
            "min_value": null,
            "std_dev": null,
            "mean": null,
            "variance": null,
            "presence": null,
            "ignore_metric": false,
            "removal_reason": null,
            "was_log_transformed": false,
            "low_variance_detected": false
        },
        {
            "metric": "spectral_centroid_diff",
            "original_weight": 0.6,
            "normalized_weight": null,
            "was_normalized": true,
            "was_inverted": false,
            "was_shared": false,
            "was_specific": false,
            "max_value": null,
            "min_value": null,
            "std_dev": null,
            "mean": null,
            "variance": null,
            "presence": null,
            "ignore_metric": false,
            "removal_reason": null,
            "was_log_transformed": false,
            "low_variance_detected": false,
            "across_mean": NaN,
            "across_std": NaN,
            "across_max": NaN,
            "across_min": NaN,
            "mean_normalized": NaN,
            "std_normalized": NaN,
            "max_normalized": NaN,
            "min_normalized": NaN
        },
        {
            "metric": "spectral_magnitude_diff",
            "original_weight": 0.6,
            "normalized_weight": null,
            "was_normalized": false,
            "was_inverted": false,
            "was_shared": false,
            "was_specific": false,
            "max_value": null,
            "min_value": null,
            "std_dev": null,
            "mean": null,
            "variance": null,
            "presence": null,
            "ignore_metric": true,
            "removal_reason": "Low variance (std: 0.000000, mean: 0.000000)",
            "was_log_transformed": false,
            "low_variance_detected": true,
            "across_mean": 0.0,
            "across_std": 0.0,
            "across_max": 0.0,
            "across_min": 0.0
        },
        {
            "metric": "dynamic_cutoff_diff",
            "original_weight": 0.5,
            "normalized_weight": null,
            "was_normalized": true,
            "was_inverted": false,
            "was_shared": false,
            "was_specific": false,
            "max_value": null,
            "min_value": null,
            "std_dev": null,
            "mean": null,
            "variance": null,
            "presence": null,
            "ignore_metric": false,
            "removal_reason": null,
            "was_log_transformed": false,
            "low_variance_detected": false,
            "across_mean": 0.0024441062044662345,
            "across_std": 0.03287797039806262,
            "across_max": 0.47824419844198474,
            "across_min": 0.0,
            "mean_normalized": 0.00511058202572786,
            "std_normalized": 0.06874724357383084,
            "max_normalized": 1.0,
            "min_normalized": 0.0
        },
        {
            "metric": "relative_prominences_total_diff",
            "original_weight": 0.5,
            "normalized_weight": null,
            "was_normalized": true,
            "was_inverted": false,
            "was_shared": false,
            "was_specific": false,
            "max_value": null,
            "min_value": null,
            "std_dev": null,
            "mean": null,
            "variance": null,
            "presence": null,
            "ignore_metric": false,
            "removal_reason": null,
            "was_log_transformed": false,
            "low_variance_detected": false,
            "across_mean": 31152.245907101078,
            "across_std": 17962.045973105105,
            "across_max": 49110.000000188375,
            "across_min": 13163.042867677403,
            "mean_normalized": 0.5004374354444028,
            "std_normalized": 0.4996819593628403,
            "max_normalized": 1.0,
            "min_normalized": 0.0
        },
        {
            "metric": "prominence_max_diff",
            "original_weight": 0.5,
            "normalized_weight": null,
            "was_normalized": true,
            "was_inverted": false,
            "was_shared": false,
            "was_specific": false,
            "max_value": null,
            "min_value": null,
            "std_dev": null,
            "mean": null,
            "variance": null,
            "presence": null,
            "ignore_metric": false,
            "removal_reason": null,
            "was_log_transformed": false,
            "low_variance_detected": false,
            "across_mean": 0.031788810948635116,
            "across_std": 0.329582899598546,
            "across_max": 3.7250081876072727,
            "across_min": 0.0,
            "mean_normalized": 0.008533890221877442,
            "std_normalized": 0.088478436287747,
            "max_normalized": 1.0,
            "min_normalized": 0.0
        },
        {
            "metric": "amplitude_max_diff",
            "original_weight": 0.5,
            "normalized_weight": null,
            "was_normalized": true,
            "was_inverted": false,
            "was_shared": false,
            "was_specific": false,
            "max_value": null,
            "min_value": null,
            "std_dev": null,
            "mean": null,
            "variance": null,
            "presence": null,
            "ignore_metric": false,
            "removal_reason": null,
            "was_log_transformed": false,
            "low_variance_detected": false,
            "across_mean": NaN,
            "across_std": NaN,
            "across_max": NaN,
            "across_min": NaN,
            "mean_normalized": NaN,
            "std_normalized": NaN,
            "max_normalized": NaN,
            "min_normalized": NaN
        },
        {
            "metric": "frequency_max_diff",
            "original_weight": 0.5,
            "normalized_weight": null,
            "was_normalized": true,
            "was_inverted": false,
            "was_shared": false,
            "was_specific": false,
            "max_value": null,
            "min_value": null,
            "std_dev": null,
            "mean": null,
            "variance": null,
            "presence": null,
            "ignore_metric": false,
            "removal_reason": null,
            "was_log_transformed": false,
            "low_variance_detected": false,
            "across_mean": NaN,
            "across_std": NaN,
            "across_max": NaN,
            "across_min": NaN,
            "mean_normalized": NaN,
            "std_normalized": NaN,
            "max_normalized": NaN,
            "min_normalized": NaN
        },
        {
            "metric": "spectral_bandwidth_diff",
            "original_weight": 0.5,
            "normalized_weight": null,
            "was_normalized": true,
            "was_inverted": false,
            "was_shared": false,
            "was_specific": false,
            "max_value": null,
            "min_value": null,
            "std_dev": null,
            "mean": null,
            "variance": null,
            "presence": null,
            "ignore_metric": false,
            "removal_reason": null,
            "was_log_transformed": false,
            "low_variance_detected": false,
            "across_mean": NaN,
            "across_std": NaN,
            "across_max": NaN,
            "across_min": NaN,
            "mean_normalized": NaN,
            "std_normalized": NaN,
            "max_normalized": NaN,
            "min_normalized": NaN
        },
        {
            "metric": "num_fft_peaks_diff",
            "original_weight": 0.4,
            "normalized_weight": null,
            "was_normalized": true,
            "was_inverted": false,
            "was_shared": false,
            "was_specific": false,
            "max_value": null,
            "min_value": null,
            "std_dev": null,
            "mean": null,
            "variance": null,
            "presence": null,
            "ignore_metric": false,
            "removal_reason": null,
            "was_log_transformed": false,
            "low_variance_detected": false,
            "across_mean": NaN,
            "across_std": NaN,
            "across_max": NaN,
            "across_min": NaN,
            "mean_normalized": NaN,
            "std_normalized": NaN,
            "max_normalized": NaN,
            "min_normalized": NaN
        },
        {
            "metric": "relative_num_peaks_diff",
            "original_weight": 0.4,
            "normalized_weight": null,
            "was_normalized": true,
            "was_inverted": false,
            "was_shared": false,
            "was_specific": false,
            "max_value": null,
            "min_value": null,
            "std_dev": null,
            "mean": null,
            "variance": null,
            "presence": null,
            "ignore_metric": false,
            "removal_reason": null,
            "was_log_transformed": false,
            "low_variance_detected": false,
            "across_mean": 76.0,
            "across_std": 10.002621575611952,
            "across_max": 86.0,
            "across_min": 66.0,
            "mean_normalized": 0.5,
            "std_normalized": 0.5001310787805976,
            "max_normalized": 1.0,
            "min_normalized": 0.0
        },
        {
            "metric": "dominant_frequency_diff",
            "original_weight": 0.5,
            "normalized_weight": null,
            "was_normalized": true,
            "was_inverted": false,
            "was_shared": false,
            "was_specific": false,
            "max_value": null,
            "min_value": null,
            "std_dev": null,
            "mean": null,
            "variance": null,
            "presence": null,
            "ignore_metric": false,
            "removal_reason": null,
            "was_log_transformed": false,
            "low_variance_detected": false,
            "across_mean": NaN,
            "across_std": NaN,
            "across_max": NaN,
            "across_min": NaN,
            "mean_normalized": NaN,
            "std_normalized": NaN,
            "max_normalized": NaN,
            "min_normalized": NaN
        },
        {
            "metric": "max_autocorrelation_diff",
            "original_weight": 0.5,
            "normalized_weight": null,
            "was_normalized": true,
            "was_inverted": false,
            "was_shared": false,
            "was_specific": false,
            "max_value": null,
            "min_value": null,
            "std_dev": null,
            "mean": null,
            "variance": null,
            "presence": null,
            "ignore_metric": false,
            "removal_reason": null,
            "was_log_transformed": false,
            "low_variance_detected": false,
            "across_mean": 3881.216435534087,
            "across_std": 41083.36040864935,
            "across_max": 523587.95562952757,
            "across_min": 0.0,
            "mean_normalized": 0.007412730552343528,
            "std_normalized": 0.0784650601048556,
            "max_normalized": 1.0,
            "min_normalized": 0.0
        },
        {
            "metric": "relative_right_bases_global_alignment_score",
            "original_weight": 0.1,
            "normalized_weight": null,
            "was_normalized": true,
            "was_inverted": false,
            "was_shared": false,
            "was_specific": false,
            "max_value": null,
            "min_value": null,
            "std_dev": null,
            "mean": null,
            "variance": null,
            "presence": null,
            "ignore_metric": false,
            "removal_reason": null,
            "was_log_transformed": false,
            "low_variance_detected": false,
            "across_mean": -30.431603773584907,
            "across_std": 8.300634742139838,
            "across_max": -14.0,
            "across_min": -44.0,
            "mean_normalized": 0.4522798742138364,
            "std_normalized": 0.2766878247379946,
            "max_normalized": 1.0,
            "min_normalized": 0.0
        },
        {
            "metric": "relative_right_bases_array_alignment_score",
            "original_weight": 0.1,
            "normalized_weight": null,
            "was_normalized": false,
            "was_inverted": false,
            "was_shared": false,
            "was_specific": false,
            "max_value": null,
            "min_value": null,
            "std_dev": null,
            "mean": null,
            "variance": null,
            "presence": null,
            "ignore_metric": true,
            "removal_reason": "Low variance (std: 0.000000, mean: 0.000000)",
            "was_log_transformed": false,
            "low_variance_detected": true,
            "across_mean": 0.0,
            "across_std": 0.0,
            "across_max": 0.0,
            "across_min": 0.0
        },
        {
            "metric": "relative_left_bases_global_alignment_score",
            "original_weight": 0.1,
            "normalized_weight": null,
            "was_normalized": true,
            "was_inverted": false,
            "was_shared": false,
            "was_specific": false,
            "max_value": null,
            "min_value": null,
            "std_dev": null,
            "mean": null,
            "variance": null,
            "presence": null,
            "ignore_metric": false,
            "removal_reason": null,
            "was_log_transformed": false,
            "low_variance_detected": false,
            "across_mean": -28.367924528301888,
            "across_std": 7.291183841802493,
            "across_max": -14.0,
            "across_min": -44.0,
            "mean_normalized": 0.521069182389937,
            "std_normalized": 0.24303946139341645,
            "max_normalized": 1.0,
            "min_normalized": 0.0
        },
        {
            "metric": "relative_left_bases_array_alignment_score",
            "original_weight": 0.1,
            "normalized_weight": null,
            "was_normalized": false,
            "was_inverted": false,
            "was_shared": false,
            "was_specific": false,
            "max_value": null,
            "min_value": null,
            "std_dev": null,
            "mean": null,
            "variance": null,
            "presence": null,
            "ignore_metric": true,
            "removal_reason": "Low variance (std: 0.000000, mean: 0.000000)",
            "was_log_transformed": false,
            "low_variance_detected": true,
            "across_mean": 0.0,
            "across_std": 0.0,
            "across_max": 0.0,
            "across_min": 0.0
        },
        {
            "metric": "upper_envelope_diff",
            "original_weight": 0.2,
            "normalized_weight": null,
            "was_normalized": true,
            "was_inverted": false,
            "was_shared": false,
            "was_specific": false,
            "max_value": null,
            "min_value": null,
            "std_dev": null,
            "mean": null,
            "variance": null,
            "presence": null,
            "ignore_metric": false,
            "removal_reason": null,
            "was_log_transformed": false,
            "low_variance_detected": false,
            "across_mean": 0.02156502753641198,
            "across_std": 0.22104068505946714,
            "across_max": 2.303975806965809,
            "across_min": 0.0,
            "mean_normalized": 0.009359919262699098,
            "std_normalized": 0.09593880473535173,
            "max_normalized": 1.0,
            "min_normalized": 0.0
        },
        {
            "metric": "lower_envelope_diff",
            "original_weight": 0.2,
            "normalized_weight": null,
            "was_normalized": true,
            "was_inverted": false,
            "was_shared": false,
            "was_specific": false,
            "max_value": null,
            "min_value": null,
            "std_dev": null,
            "mean": null,
            "variance": null,
            "presence": null,
            "ignore_metric": false,
            "removal_reason": null,
            "was_log_transformed": false,
            "low_variance_detected": false,
            "across_mean": 0.02156502753641198,
            "across_std": 0.22104068505946714,
            "across_max": 2.303975806965809,
            "across_min": 0.0,
            "mean_normalized": 0.009359919262699098,
            "std_normalized": 0.09593880473535173,
            "max_normalized": 1.0,
            "min_normalized": 0.0
        },
        {
            "metric": "relative_peaks_array_alignment_score",
            "original_weight": 0.2,
            "normalized_weight": null,
            "was_normalized": false,
            "was_inverted": false,
            "was_shared": false,
            "was_specific": false,
            "max_value": null,
            "min_value": null,
            "std_dev": null,
            "mean": null,
            "variance": null,
            "presence": null,
            "ignore_metric": true,
            "removal_reason": "Low variance (std: 0.000000, mean: 0.000000)",
            "was_log_transformed": false,
            "low_variance_detected": true,
            "across_mean": 0.0,
            "across_std": 0.0,
            "across_max": 0.0,
            "across_min": 0.0
        },
        {
            "metric": "relative_peaks_global_alignment_score",
            "original_weight": 0.2,
            "normalized_weight": null,
            "was_normalized": true,
            "was_inverted": false,
            "was_shared": false,
            "was_specific": false,
            "max_value": null,
            "min_value": null,
            "std_dev": null,
            "mean": null,
            "variance": null,
            "presence": null,
            "ignore_metric": false,
            "removal_reason": null,
            "was_log_transformed": false,
            "low_variance_detected": false,
            "across_mean": -22.25,
            "across_std": 8.25216279987986,
            "across_max": -14.0,
            "across_min": -30.5,
            "mean_normalized": 0.5,
            "std_normalized": 0.5001310787805976,
            "max_normalized": 1.0,
            "min_normalized": 0.0
        }
    ],
    "comparison_prefix": "across_",
    "reconstruction_normalized_weighted_max": 1.0,
    "reconstruction_normalized_weighted_min": 0.2868347985725601,
    "reconstruction_normalized_weighted_mean": 0.39249740030682967,
    "reconstruction_normalized_weighted_std": 0.09834637127235517,
    "signal_normalized_weighted_max": 1.0,
    "signal_normalized_weighted_min": 0.43283792461006115,
    "signal_normalized_weighted_mean": 0.6329077995530735,
    "signal_normalized_weighted_std": 0.10356774708603944,
    "ranking_columns": [
        "across_reconstruction_normalized_weighted_rank",
        "across_signal_normalized_weighted_rank"
    ],
    "across_selected_family_rank_stability_column": "across_family_informed_rank",
    "across_selected_family_rank_stability_column_correlation": 0.9999996438173953
}