{
    "signal_type": "smoothed",
    "metrics": [
        {
            "metric": "emd_value",
            "original_weight": 0.3,
            "normalized_weight": 0.14285714285714285,
            "was_normalized": true,
            "was_inverted": false,
            "was_shared": false,
            "was_specific": false,
            "max_value": null,
            "min_value": null,
            "std_dev": null,
            "mean": 90796.21548808004,
            "variance": null,
            "presence": null,
            "ignore_metric": false,
            "removal_reason": null,
            "was_log_transformed": false,
            "low_variance_detected": false,
            "final_weight": 0.14285714285714285,
            "std": 64306.16447089147,
            "max": 215390.30434511416,
            "min": 32409.716455199,
            "mean_normalized": 0.3190857549764107,
            "std_normalized": 0.351437085280212,
            "max_normalized": 0.9999999999999999,
            "min_normalized": 0.0
        },
        {
            "metric": "smoothness",
            "original_weight": 0.3,
            "normalized_weight": null,
            "was_normalized": false,
            "was_inverted": false,
            "was_shared": false,
            "was_specific": false,
            "max_value": null,
            "min_value": null,
            "std_dev": null,
            "mean": 1.1022940368747252e-06,
            "variance": null,
            "presence": null,
            "ignore_metric": true,
            "removal_reason": "Low variance (std: 0.000000, mean: 0.000001)",
            "was_log_transformed": false,
            "low_variance_detected": true,
            "std": 4.2735484813994094e-07,
            "max": 1.843446599903336e-06,
            "min": 4.718890254413263e-07
        },
        {
            "metric": "wavelet_mse",
            "original_weight": 0.6,
            "normalized_weight": null,
            "was_normalized": false,
            "was_inverted": false,
            "was_shared": false,
            "was_specific": false,
            "max_value": null,
            "min_value": null,
            "std_dev": null,
            "mean": null,
            "variance": null,
            "presence": null,
            "ignore_metric": false,
            "removal_reason": null,
            "was_log_transformed": false,
            "low_variance_detected": false
        },
        {
            "metric": "wavelet_psnr",
            "original_weight": 0.6,
            "normalized_weight": 0.14285714285714285,
            "was_normalized": true,
            "was_inverted": false,
            "was_shared": false,
            "was_specific": false,
            "max_value": null,
            "min_value": null,
            "std_dev": null,
            "mean": -37.723943424313646,
            "variance": null,
            "presence": null,
            "ignore_metric": false,
            "removal_reason": null,
            "was_log_transformed": false,
            "low_variance_detected": false,
            "final_weight": 0.14285714285714285,
            "std": 5.171435834650002,
            "max": -30.381987635494223,
            "min": -45.85440794057437,
            "mean_normalized": 0.5254811048269676,
            "std_normalized": 0.3342357389911413,
            "max_normalized": 1.0,
            "min_normalized": 0.0
        },
        {
            "metric": "wavelet_entropy",
            "original_weight": 0.5,
            "normalized_weight": 0.14285714285714285,
            "was_normalized": true,
            "was_inverted": false,
            "was_shared": false,
            "was_specific": false,
            "max_value": null,
            "min_value": null,
            "std_dev": null,
            "mean": 13.446034626713436,
            "variance": null,
            "presence": null,
            "ignore_metric": false,
            "removal_reason": null,
            "was_log_transformed": false,
            "low_variance_detected": false,
            "final_weight": 0.14285714285714285,
            "std": 0.10633899112476275,
            "max": 13.569542482032489,
            "min": 13.226756436392037,
            "mean_normalized": 0.6396940397958917,
            "std_normalized": 0.3102197200766502,
            "max_normalized": 1.0,
            "min_normalized": 0.0
        },
        {
            "metric": "wavelet_energy_entropy",
            "original_weight": 0.5,
            "normalized_weight": 0.14285714285714285,
            "was_normalized": true,
            "was_inverted": false,
            "was_shared": false,
            "was_specific": false,
            "max_value": null,
            "min_value": null,
            "std_dev": null,
            "mean": 3806226603.1729116,
            "variance": null,
            "presence": null,
            "ignore_metric": false,
            "removal_reason": null,
            "was_log_transformed": false,
            "low_variance_detected": false,
            "final_weight": 0.14285714285714285,
            "std": 4291786969.462575,
            "max": 12597162617.430084,
            "min": 714737143.5066284,
            "mean_normalized": 0.26017326735612223,
            "std_normalized": 0.36118778770219134,
            "max_normalized": 1.0,
            "min_normalized": 0.0
        },
        {
            "metric": "wavelet_sparsity",
            "original_weight": 0.4,
            "normalized_weight": 0.14285714285714285,
            "was_normalized": true,
            "was_inverted": false,
            "was_shared": false,
            "was_specific": false,
            "max_value": null,
            "min_value": null,
            "std_dev": null,
            "mean": 0.6401630988786952,
            "variance": null,
            "presence": null,
            "ignore_metric": false,
            "removal_reason": null,
            "was_log_transformed": false,
            "low_variance_detected": false,
            "final_weight": 0.14285714285714285,
            "std": 0.023230606285352163,
            "max": 0.6683656133197418,
            "min": 0.5826112810057764,
            "mean_normalized": 0.6711243189697871,
            "std_normalized": 0.27089717403780655,
            "max_normalized": 1.0000000000000002,
            "min_normalized": 0.0
        },
        {
            "metric": "correlation",
            "original_weight": 0.4,
            "normalized_weight": 0.14285714285714285,
            "was_normalized": true,
            "was_inverted": false,
            "was_shared": false,
            "was_specific": false,
            "max_value": null,
            "min_value": null,
            "std_dev": null,
            "mean": 0.18368758786171835,
            "variance": null,
            "presence": null,
            "ignore_metric": false,
            "removal_reason": null,
            "was_log_transformed": false,
            "low_variance_detected": false,
            "final_weight": 0.14285714285714285,
            "std": 0.21976783077490103,
            "max": 0.44170914554728774,
            "min": -0.110655730138319,
            "mean_normalized": 0.5328784123622856,
            "std_normalized": 0.39786713538242385,
            "max_normalized": 1.0,
            "min_normalized": 0.0
        },
        {
            "metric": "avg_variance_across_levels",
            "original_weight": 0.4,
            "normalized_weight": 0.14285714285714285,
            "was_normalized": true,
            "was_inverted": false,
            "was_shared": false,
            "was_specific": false,
            "max_value": null,
            "min_value": null,
            "std_dev": null,
            "mean": 1278020.4952139205,
            "variance": null,
            "presence": null,
            "ignore_metric": false,
            "removal_reason": null,
            "was_log_transformed": false,
            "low_variance_detected": false,
            "final_weight": 0.14285714285714285,
            "std": 1653779.4580238224,
            "max": 5887728.645822801,
            "min": 383463.4494070472,
            "mean_normalized": 0.1625207023799267,
            "std_normalized": 0.3004541749007159,
            "max_normalized": 1.0,
            "min_normalized": 0.0
        },
        {
            "metric": "kl_divergence",
            "original_weight": 0.4,
            "normalized_weight": null,
            "was_normalized": true,
            "was_inverted": false,
            "was_shared": false,
            "was_specific": false,
            "max_value": null,
            "min_value": null,
            "std_dev": null,
            "mean": NaN,
            "variance": null,
            "presence": null,
            "ignore_metric": true,
            "removal_reason": "Presence: 0.00, Variance: nan (below 0.1)",
            "was_log_transformed": false,
            "low_variance_detected": false,
            "std": NaN,
            "max": NaN,
            "min": NaN,
            "mean_normalized": NaN,
            "std_normalized": NaN,
            "max_normalized": NaN,
            "min_normalized": NaN
        },
        {
            "metric": "prominence_min_diff",
            "original_weight": 0.3,
            "normalized_weight": 0.07142857142857144,
            "was_normalized": true,
            "was_inverted": false,
            "was_shared": false,
            "was_specific": false,
            "max_value": null,
            "min_value": null,
            "std_dev": null,
            "mean": 11030.408862462726,
            "variance": null,
            "presence": null,
            "ignore_metric": false,
            "removal_reason": null,
            "was_log_transformed": false,
            "low_variance_detected": false,
            "final_weight": 0.07142857142857144,
            "std": 6945.241872323817,
            "max": 23329.839604531582,
            "min": 3827.718262320775,
            "mean_normalized": 0.36932857065924896,
            "std_normalized": 0.3561275078978915,
            "max_normalized": 1.0,
            "min_normalized": 0.0
        },
        {
            "metric": "positive_amplitudes_dtw",
            "original_weight": 0.35,
            "normalized_weight": null,
            "was_normalized": false,
            "was_inverted": false,
            "was_shared": false,
            "was_specific": false,
            "max_value": null,
            "min_value": null,
            "std_dev": null,
            "mean": null,
            "variance": null,
            "presence": null,
            "ignore_metric": false,
            "removal_reason": null,
            "was_log_transformed": false,
            "low_variance_detected": false
        },
        {
            "metric": "positive_amplitudes_euclidean",
            "original_weight": 0.35,
            "normalized_weight": null,
            "was_normalized": false,
            "was_inverted": false,
            "was_shared": false,
            "was_specific": false,
            "max_value": null,
            "min_value": null,
            "std_dev": null,
            "mean": null,
            "variance": null,
            "presence": null,
            "ignore_metric": false,
            "removal_reason": null,
            "was_log_transformed": false,
            "low_variance_detected": false
        },
        {
            "metric": "positive_amplitudes_wasserstein",
            "original_weight": 0.35,
            "normalized_weight": null,
            "was_normalized": false,
            "was_inverted": false,
            "was_shared": false,
            "was_specific": false,
            "max_value": null,
            "min_value": null,
            "std_dev": null,
            "mean": null,
            "variance": null,
            "presence": null,
            "ignore_metric": false,
            "removal_reason": null,
            "was_log_transformed": false,
            "low_variance_detected": false
        },
        {
            "metric": "avg_prominence_diff",
            "original_weight": 0.3,
            "normalized_weight": 0.07142857142857144,
            "was_normalized": true,
            "was_inverted": false,
            "was_shared": false,
            "was_specific": false,
            "max_value": null,
            "min_value": null,
            "std_dev": null,
            "mean": 75219.85918023491,
            "variance": null,
            "presence": null,
            "ignore_metric": false,
            "removal_reason": null,
            "was_log_transformed": false,
            "low_variance_detected": false,
            "final_weight": 0.07142857142857144,
            "std": 34678.96704592024,
            "max": 150918.80716227787,
            "min": 34971.12270301071,
            "mean_normalized": 0.3471284197259129,
            "std_normalized": 0.2990915015478648,
            "max_normalized": 1.0,
            "min_normalized": 0.0
        },
        {
            "metric": "relative_prominences_avg_diff",
            "original_weight": 0.3,
            "normalized_weight": 0.07142857142857144,
            "was_normalized": true,
            "was_inverted": false,
            "was_shared": false,
            "was_specific": false,
            "max_value": null,
            "min_value": null,
            "std_dev": null,
            "mean": 75219.85918023491,
            "variance": null,
            "presence": null,
            "ignore_metric": false,
            "removal_reason": null,
            "was_log_transformed": false,
            "low_variance_detected": false,
            "final_weight": 0.07142857142857144,
            "std": 34678.96704592024,
            "max": 150918.80716227787,
            "min": 34971.12270301071,
            "mean_normalized": 0.3471284197259129,
            "std_normalized": 0.2990915015478648,
            "max_normalized": 1.0,
            "min_normalized": 0.0
        },
        {
            "metric": "relative_prominences_wasserstein",
            "original_weight": 0.3,
            "normalized_weight": 0.07142857142857144,
            "was_normalized": true,
            "was_inverted": false,
            "was_shared": false,
            "was_specific": false,
            "max_value": null,
            "min_value": null,
            "std_dev": null,
            "mean": 75219.85918023491,
            "variance": null,
            "presence": null,
            "ignore_metric": false,
            "removal_reason": null,
            "was_log_transformed": false,
            "low_variance_detected": false,
            "final_weight": 0.07142857142857144,
            "std": 34678.96704592024,
            "max": 150918.80716227787,
            "min": 34971.12270301071,
            "mean_normalized": 0.347128419725913,
            "std_normalized": 0.2990915015478648,
            "max_normalized": 1.0,
            "min_normalized": 0.0
        },
        {
            "metric": "positive_frequencies_dtw",
            "original_weight": 0.35,
            "normalized_weight": null,
            "was_normalized": false,
            "was_inverted": false,
            "was_shared": false,
            "was_specific": false,
            "max_value": null,
            "min_value": null,
            "std_dev": null,
            "mean": null,
            "variance": null,
            "presence": null,
            "ignore_metric": false,
            "removal_reason": null,
            "was_log_transformed": false,
            "low_variance_detected": false
        },
        {
            "metric": "positive_frequencies_euclidean",
            "original_weight": 0.35,
            "normalized_weight": null,
            "was_normalized": false,
            "was_inverted": false,
            "was_shared": false,
            "was_specific": false,
            "max_value": null,
            "min_value": null,
            "std_dev": null,
            "mean": null,
            "variance": null,
            "presence": null,
            "ignore_metric": false,
            "removal_reason": null,
            "was_log_transformed": false,
            "low_variance_detected": false
        },
        {
            "metric": "positive_frequencies_wasserstein",
            "original_weight": 0.35,
            "normalized_weight": null,
            "was_normalized": false,
            "was_inverted": false,
            "was_shared": false,
            "was_specific": false,
            "max_value": null,
            "min_value": null,
            "std_dev": null,
            "mean": null,
            "variance": null,
            "presence": null,
            "ignore_metric": false,
            "removal_reason": null,
            "was_log_transformed": false,
            "low_variance_detected": false
        },
        {
            "metric": "spectral_centroid_diff",
            "original_weight": 0.6,
            "normalized_weight": null,
            "was_normalized": true,
            "was_inverted": false,
            "was_shared": false,
            "was_specific": false,
            "max_value": null,
            "min_value": null,
            "std_dev": null,
            "mean": NaN,
            "variance": null,
            "presence": null,
            "ignore_metric": true,
            "removal_reason": "Presence: 0.00, Variance: nan (below 0.1)",
            "was_log_transformed": false,
            "low_variance_detected": false,
            "std": NaN,
            "max": NaN,
            "min": NaN,
            "mean_normalized": NaN,
            "std_normalized": NaN,
            "max_normalized": NaN,
            "min_normalized": NaN
        },
        {
            "metric": "spectral_magnitude_diff",
            "original_weight": 0.6,
            "normalized_weight": null,
            "was_normalized": false,
            "was_inverted": false,
            "was_shared": false,
            "was_specific": false,
            "max_value": null,
            "min_value": null,
            "std_dev": null,
            "mean": 0.0,
            "variance": null,
            "presence": null,
            "ignore_metric": true,
            "removal_reason": "Low variance (std: 0.000000, mean: 0.000000)",
            "was_log_transformed": false,
            "low_variance_detected": true,
            "std": 0.0,
            "max": 0.0,
            "min": 0.0
        },
        {
            "metric": "dynamic_cutoff_diff",
            "original_weight": 0.5,
            "normalized_weight": 0.07142857142857144,
            "was_normalized": true,
            "was_inverted": false,
            "was_shared": false,
            "was_specific": false,
            "max_value": null,
            "min_value": null,
            "std_dev": null,
            "mean": 48309.400765691724,
            "variance": null,
            "presence": null,
            "ignore_metric": false,
            "removal_reason": null,
            "was_log_transformed": false,
            "low_variance_detected": false,
            "final_weight": 0.07142857142857144,
            "std": 77693.45608356928,
            "max": 237463.30456945792,
            "min": 587.1,
            "mean_normalized": 0.20146515287354821,
            "std_normalized": 0.3279918142254245,
            "max_normalized": 0.9999999999999999,
            "min_normalized": 0.0
        },
        {
            "metric": "relative_prominences_total_diff",
            "original_weight": 0.5,
            "normalized_weight": 0.07142857142857144,
            "was_normalized": true,
            "was_inverted": false,
            "was_shared": false,
            "was_specific": false,
            "max_value": null,
            "min_value": null,
            "std_dev": null,
            "mean": 246006.0867721236,
            "variance": null,
            "presence": null,
            "ignore_metric": false,
            "removal_reason": null,
            "was_log_transformed": false,
            "low_variance_detected": false,
            "final_weight": 0.07142857142857144,
            "std": 84342.10395792885,
            "max": 308354.18432709645,
            "min": 67847.41829271647,
            "mean_normalized": 0.7407636442707797,
            "std_normalized": 0.3506849530622864,
            "max_normalized": 1.0,
            "min_normalized": 0.0
        },
        {
            "metric": "prominence_max_diff",
            "original_weight": 0.5,
            "normalized_weight": 0.07142857142857144,
            "was_normalized": true,
            "was_inverted": false,
            "was_shared": false,
            "was_specific": false,
            "max_value": null,
            "min_value": null,
            "std_dev": null,
            "mean": 162278.8228736185,
            "variance": null,
            "presence": null,
            "ignore_metric": false,
            "removal_reason": null,
            "was_log_transformed": false,
            "low_variance_detected": false,
            "final_weight": 0.07142857142857144,
            "std": 66692.90201622146,
            "max": 293523.7019267747,
            "min": 54768.69328793139,
            "mean_normalized": 0.45029476113866196,
            "std_normalized": 0.27933613789483086,
            "max_normalized": 1.0,
            "min_normalized": 0.0
        },
        {
            "metric": "amplitude_max_diff",
            "original_weight": 0.5,
            "normalized_weight": null,
            "was_normalized": true,
            "was_inverted": false,
            "was_shared": false,
            "was_specific": false,
            "max_value": null,
            "min_value": null,
            "std_dev": null,
            "mean": NaN,
            "variance": null,
            "presence": null,
            "ignore_metric": true,
            "removal_reason": "Presence: 0.00, Variance: nan (below 0.1)",
            "was_log_transformed": false,
            "low_variance_detected": false,
            "std": NaN,
            "max": NaN,
            "min": NaN,
            "mean_normalized": NaN,
            "std_normalized": NaN,
            "max_normalized": NaN,
            "min_normalized": NaN
        },
        {
            "metric": "frequency_max_diff",
            "original_weight": 0.5,
            "normalized_weight": null,
            "was_normalized": true,
            "was_inverted": false,
            "was_shared": false,
            "was_specific": false,
            "max_value": null,
            "min_value": null,
            "std_dev": null,
            "mean": NaN,
            "variance": null,
            "presence": null,
            "ignore_metric": true,
            "removal_reason": "Presence: 0.00, Variance: nan (below 0.1)",
            "was_log_transformed": false,
            "low_variance_detected": false,
            "std": NaN,
            "max": NaN,
            "min": NaN,
            "mean_normalized": NaN,
            "std_normalized": NaN,
            "max_normalized": NaN,
            "min_normalized": NaN
        },
        {
            "metric": "spectral_bandwidth_diff",
            "original_weight": 0.5,
            "normalized_weight": null,
            "was_normalized": true,
            "was_inverted": false,
            "was_shared": false,
            "was_specific": false,
            "max_value": null,
            "min_value": null,
            "std_dev": null,
            "mean": NaN,
            "variance": null,
            "presence": null,
            "ignore_metric": true,
            "removal_reason": "Presence: 0.00, Variance: nan (below 0.1)",
            "was_log_transformed": false,
            "low_variance_detected": false,
            "std": NaN,
            "max": NaN,
            "min": NaN,
            "mean_normalized": NaN,
            "std_normalized": NaN,
            "max_normalized": NaN,
            "min_normalized": NaN
        },
        {
            "metric": "num_fft_peaks_diff",
            "original_weight": 0.4,
            "normalized_weight": null,
            "was_normalized": true,
            "was_inverted": false,
            "was_shared": false,
            "was_specific": false,
            "max_value": null,
            "min_value": null,
            "std_dev": null,
            "mean": NaN,
            "variance": null,
            "presence": null,
            "ignore_metric": true,
            "removal_reason": "Presence: 0.00, Variance: nan (below 0.1)",
            "was_log_transformed": false,
            "low_variance_detected": false,
            "std": NaN,
            "max": NaN,
            "min": NaN,
            "mean_normalized": NaN,
            "std_normalized": NaN,
            "max_normalized": NaN,
            "min_normalized": NaN
        },
        {
            "metric": "relative_num_peaks_diff",
            "original_weight": 0.4,
            "normalized_weight": 0.07142857142857144,
            "was_normalized": true,
            "was_inverted": false,
            "was_shared": false,
            "was_specific": false,
            "max_value": null,
            "min_value": null,
            "std_dev": null,
            "mean": 21.5,
            "variance": null,
            "presence": null,
            "ignore_metric": false,
            "removal_reason": null,
            "was_log_transformed": false,
            "low_variance_detected": false,
            "final_weight": 0.07142857142857144,
            "std": 2.4608038433722332,
            "max": 25.0,
            "min": 16.0,
            "mean_normalized": 0.611111111111111,
            "std_normalized": 0.2734226492635815,
            "max_normalized": 1.0,
            "min_normalized": 0.0
        },
        {
            "metric": "dominant_frequency_diff",
            "original_weight": 0.5,
            "normalized_weight": null,
            "was_normalized": true,
            "was_inverted": false,
            "was_shared": false,
            "was_specific": false,
            "max_value": null,
            "min_value": null,
            "std_dev": null,
            "mean": NaN,
            "variance": null,
            "presence": null,
            "ignore_metric": true,
            "removal_reason": "Presence: 0.00, Variance: nan (below 0.1)",
            "was_log_transformed": false,
            "low_variance_detected": false,
            "std": NaN,
            "max": NaN,
            "min": NaN,
            "mean_normalized": NaN,
            "std_normalized": NaN,
            "max_normalized": NaN,
            "min_normalized": NaN
        },
        {
            "metric": "max_autocorrelation_diff",
            "original_weight": 0.5,
            "normalized_weight": 0.07142857142857144,
            "was_normalized": true,
            "was_inverted": false,
            "was_shared": false,
            "was_specific": false,
            "max_value": null,
            "min_value": null,
            "std_dev": null,
            "mean": 3397343251053.228,
            "variance": null,
            "presence": null,
            "ignore_metric": false,
            "removal_reason": null,
            "was_log_transformed": false,
            "low_variance_detected": false,
            "final_weight": 0.07142857142857144,
            "std": 4273168988044.4033,
            "max": 11360029776002.785,
            "min": 325272150259.333,
            "mean_normalized": 0.27839950862417956,
            "std_normalized": 0.3872462933010279,
            "max_normalized": 0.9999999999999999,
            "min_normalized": 0.0
        },
        {
            "metric": "relative_right_bases_global_alignment_score",
            "original_weight": 0.1,
            "normalized_weight": 0.07142857142857144,
            "was_normalized": true,
            "was_inverted": false,
            "was_shared": false,
            "was_specific": false,
            "max_value": null,
            "min_value": null,
            "std_dev": null,
            "mean": -17.555555555555557,
            "variance": null,
            "presence": null,
            "ignore_metric": false,
            "removal_reason": null,
            "was_log_transformed": false,
            "low_variance_detected": false,
            "final_weight": 0.07142857142857144,
            "std": 5.976226048082333,
            "max": -9.0,
            "min": -24.0,
            "mean_normalized": 0.4296296296296296,
            "std_normalized": 0.3984150698721555,
            "max_normalized": 1.0,
            "min_normalized": 0.0
        },
        {
            "metric": "relative_right_bases_array_alignment_score",
            "original_weight": 0.1,
            "normalized_weight": null,
            "was_normalized": false,
            "was_inverted": false,
            "was_shared": false,
            "was_specific": false,
            "max_value": null,
            "min_value": null,
            "std_dev": null,
            "mean": 0.0,
            "variance": null,
            "presence": null,
            "ignore_metric": true,
            "removal_reason": "Low variance (std: 0.000000, mean: 0.000000)",
            "was_log_transformed": false,
            "low_variance_detected": true,
            "std": 0.0,
            "max": 0.0,
            "min": 0.0
        },
        {
            "metric": "relative_left_bases_global_alignment_score",
            "original_weight": 0.1,
            "normalized_weight": 0.07142857142857144,
            "was_normalized": true,
            "was_inverted": false,
            "was_shared": false,
            "was_specific": false,
            "max_value": null,
            "min_value": null,
            "std_dev": null,
            "mean": -21.055555555555557,
            "variance": null,
            "presence": null,
            "ignore_metric": false,
            "removal_reason": null,
            "was_log_transformed": false,
            "low_variance_detected": false,
            "final_weight": 0.07142857142857144,
            "std": 4.419024527854284,
            "max": -13.5,
            "min": -24.0,
            "mean_normalized": 0.2804232804232804,
            "std_normalized": 0.4208594788432651,
            "max_normalized": 1.0,
            "min_normalized": 0.0
        },
        {
            "metric": "relative_left_bases_array_alignment_score",
            "original_weight": 0.1,
            "normalized_weight": null,
            "was_normalized": false,
            "was_inverted": false,
            "was_shared": false,
            "was_specific": false,
            "max_value": null,
            "min_value": null,
            "std_dev": null,
            "mean": 0.0,
            "variance": null,
            "presence": null,
            "ignore_metric": true,
            "removal_reason": "Low variance (std: 0.000000, mean: 0.000000)",
            "was_log_transformed": false,
            "low_variance_detected": true,
            "std": 0.0,
            "max": 0.0,
            "min": 0.0
        },
        {
            "metric": "upper_envelope_diff",
            "original_weight": 0.2,
            "normalized_weight": 0.07142857142857144,
            "was_normalized": true,
            "was_inverted": false,
            "was_shared": false,
            "was_specific": false,
            "max_value": null,
            "min_value": null,
            "std_dev": null,
            "mean": 186417.88382487354,
            "variance": null,
            "presence": null,
            "ignore_metric": false,
            "removal_reason": null,
            "was_log_transformed": false,
            "low_variance_detected": false,
            "final_weight": 0.07142857142857144,
            "std": 103253.07468424592,
            "max": 410798.5213753103,
            "min": 73941.16525014327,
            "mean_normalized": 0.33390014060710316,
            "std_normalized": 0.30651868752980377,
            "max_normalized": 1.0,
            "min_normalized": 0.0
        },
        {
            "metric": "lower_envelope_diff",
            "original_weight": 0.2,
            "normalized_weight": 0.07142857142857144,
            "was_normalized": true,
            "was_inverted": false,
            "was_shared": false,
            "was_specific": false,
            "max_value": null,
            "min_value": null,
            "std_dev": null,
            "mean": 186417.88382487354,
            "variance": null,
            "presence": null,
            "ignore_metric": false,
            "removal_reason": null,
            "was_log_transformed": false,
            "low_variance_detected": false,
            "final_weight": 0.07142857142857144,
            "std": 103253.07468424592,
            "max": 410798.5213753103,
            "min": 73941.16525014327,
            "mean_normalized": 0.33390014060710316,
            "std_normalized": 0.30651868752980377,
            "max_normalized": 1.0,
            "min_normalized": 0.0
        },
        {
            "metric": "relative_peaks_array_alignment_score",
            "original_weight": 0.2,
            "normalized_weight": null,
            "was_normalized": false,
            "was_inverted": false,
            "was_shared": false,
            "was_specific": false,
            "max_value": null,
            "min_value": null,
            "std_dev": null,
            "mean": 0.0,
            "variance": null,
            "presence": null,
            "ignore_metric": true,
            "removal_reason": "Low variance (std: 0.000000, mean: 0.000000)",
            "was_log_transformed": false,
            "low_variance_detected": true,
            "std": 0.0,
            "max": 0.0,
            "min": 0.0
        },
        {
            "metric": "relative_peaks_global_alignment_score",
            "original_weight": 0.2,
            "normalized_weight": 0.07142857142857144,
            "was_normalized": true,
            "was_inverted": false,
            "was_shared": false,
            "was_specific": false,
            "max_value": null,
            "min_value": null,
            "std_dev": null,
            "mean": -17.555555555555557,
            "variance": null,
            "presence": null,
            "ignore_metric": false,
            "removal_reason": null,
            "was_log_transformed": false,
            "low_variance_detected": false,
            "final_weight": 0.07142857142857144,
            "std": 6.853121754191864,
            "max": -2.5,
            "min": -24.0,
            "mean_normalized": 0.2997416020671835,
            "std_normalized": 0.31874984903217973,
            "max_normalized": 1.0,
            "min_normalized": 0.0
        }
    ],
    "penalty_weight": 0.05,
    "reconstruction_normalized_weighted_max": 1.0,
    "reconstruction_normalized_weighted_min": 0.2476005593799167,
    "reconstruction_normalized_weighted_mean": 0.46228101883572503,
    "reconstruction_normalized_weighted_std": 0.21989388581074004,
    "signal_normalized_weighted_max": 1.0,
    "signal_normalized_weighted_min": 0.443861447095622,
    "signal_normalized_weighted_mean": 0.781754800163199,
    "signal_normalized_weighted_std": 0.15567359983939769,
    "ranking_columns": [
        "reconstruction_normalized_weighted_rank",
        "reconstruction_normalized_dynamically_weighted_rank",
        "signal_normalized_weighted_rank",
        "signal_normalized_dynamically_weighted_rank"
    ],
    "selected_family_rank_stability_column": "family_informed_rank",
    "selected_family_rank_stability_column_correlation": 0.9972634851342234
}