{
    "signal_type": "raw",
    "metrics": [
        {
            "metric": "emd_value",
            "original_weight": 0.3,
            "normalized_weight": 0.125,
            "was_normalized": true,
            "was_inverted": false,
            "was_shared": false,
            "was_specific": false,
            "max_value": null,
            "min_value": null,
            "std_dev": null,
            "mean": 45957.19543340001,
            "variance": null,
            "presence": null,
            "ignore_metric": false,
            "removal_reason": null,
            "was_log_transformed": false,
            "low_variance_detected": false,
            "final_weight": 0.125,
            "std": 26017.141460646406,
            "max": 95724.59144656835,
            "min": 18764.14921599051,
            "mean_normalized": 0.3533379672629427,
            "std_normalized": 0.3380586273490682,
            "max_normalized": 1.0,
            "min_normalized": 0.0
        },
        {
            "metric": "smoothness",
            "original_weight": 0.3,
            "normalized_weight": null,
            "was_normalized": false,
            "was_inverted": false,
            "was_shared": false,
            "was_specific": false,
            "max_value": null,
            "min_value": null,
            "std_dev": null,
            "mean": 7.279040399888478e-07,
            "variance": null,
            "presence": null,
            "ignore_metric": true,
            "removal_reason": "Low variance (std: 0.000000, mean: 0.000001)",
            "was_log_transformed": false,
            "low_variance_detected": true,
            "std": 3.02419983343786e-07,
            "max": 1.3294323257527084e-06,
            "min": 3.986701706003399e-07
        },
        {
            "metric": "wavelet_mse",
            "original_weight": 0.6,
            "normalized_weight": null,
            "was_normalized": false,
            "was_inverted": false,
            "was_shared": false,
            "was_specific": false,
            "max_value": null,
            "min_value": null,
            "std_dev": null,
            "mean": null,
            "variance": null,
            "presence": null,
            "ignore_metric": false,
            "removal_reason": null,
            "was_log_transformed": false,
            "low_variance_detected": false
        },
        {
            "metric": "wavelet_psnr",
            "original_weight": 0.6,
            "normalized_weight": 0.125,
            "was_normalized": true,
            "was_inverted": false,
            "was_shared": false,
            "was_specific": false,
            "max_value": null,
            "min_value": null,
            "std_dev": null,
            "mean": -34.79422674464652,
            "variance": null,
            "presence": null,
            "ignore_metric": false,
            "removal_reason": null,
            "was_log_transformed": false,
            "low_variance_detected": false,
            "final_weight": 0.125,
            "std": 4.281202586069679,
            "max": -28.502668648810086,
            "min": -41.57345749321091,
            "mean_normalized": 0.5186550581810088,
            "std_normalized": 0.32753972518679564,
            "max_normalized": 1.0,
            "min_normalized": 0.0
        },
        {
            "metric": "wavelet_entropy",
            "original_weight": 0.5,
            "normalized_weight": 0.125,
            "was_normalized": true,
            "was_inverted": false,
            "was_shared": false,
            "was_specific": false,
            "max_value": null,
            "min_value": null,
            "std_dev": null,
            "mean": 12.602727943395138,
            "variance": null,
            "presence": null,
            "ignore_metric": false,
            "removal_reason": null,
            "was_log_transformed": false,
            "low_variance_detected": false,
            "final_weight": 0.125,
            "std": 0.07810563830382097,
            "max": 12.710836791087559,
            "min": 12.460713192058211,
            "mean_normalized": 0.5677782979616525,
            "std_normalized": 0.3122681690449238,
            "max_normalized": 1.0,
            "min_normalized": 0.0
        },
        {
            "metric": "wavelet_energy_entropy",
            "original_weight": 0.5,
            "normalized_weight": 0.125,
            "was_normalized": true,
            "was_inverted": false,
            "was_shared": false,
            "was_specific": false,
            "max_value": null,
            "min_value": null,
            "std_dev": null,
            "mean": 953700133.7232101,
            "variance": null,
            "presence": null,
            "ignore_metric": false,
            "removal_reason": null,
            "was_log_transformed": false,
            "low_variance_detected": false,
            "final_weight": 0.125,
            "std": 893258130.836462,
            "max": 2813380539.273109,
            "min": 243894771.66389206,
            "mean_normalized": 0.2762441306377649,
            "std_normalized": 0.34764081673337927,
            "max_normalized": 1.0,
            "min_normalized": 0.0
        },
        {
            "metric": "wavelet_sparsity",
            "original_weight": 0.4,
            "normalized_weight": 0.125,
            "was_normalized": true,
            "was_inverted": false,
            "was_shared": false,
            "was_specific": false,
            "max_value": null,
            "min_value": null,
            "std_dev": null,
            "mean": 0.6566772151898734,
            "variance": null,
            "presence": null,
            "ignore_metric": false,
            "removal_reason": null,
            "was_log_transformed": false,
            "low_variance_detected": false,
            "final_weight": 0.125,
            "std": 0.026725553205616485,
            "max": 0.7048259493670886,
            "min": 0.6230221518987342,
            "mean_normalized": 0.4114119922630556,
            "std_normalized": 0.32670308754254584,
            "max_normalized": 1.0,
            "min_normalized": 0.0
        },
        {
            "metric": "correlation",
            "original_weight": 0.4,
            "normalized_weight": 0.125,
            "was_normalized": true,
            "was_inverted": false,
            "was_shared": false,
            "was_specific": false,
            "max_value": null,
            "min_value": null,
            "std_dev": null,
            "mean": 0.24315024564354468,
            "variance": null,
            "presence": null,
            "ignore_metric": false,
            "removal_reason": null,
            "was_log_transformed": false,
            "low_variance_detected": false,
            "final_weight": 0.125,
            "std": 0.22700894082894563,
            "max": 0.4612509810346428,
            "min": -0.14801141696473652,
            "mean_normalized": 0.6420249532758456,
            "std_normalized": 0.3725963420266367,
            "max_normalized": 1.0,
            "min_normalized": 0.0
        },
        {
            "metric": "avg_variance_across_levels",
            "original_weight": 0.4,
            "normalized_weight": 0.125,
            "was_normalized": true,
            "was_inverted": false,
            "was_shared": false,
            "was_specific": false,
            "max_value": null,
            "min_value": null,
            "std_dev": null,
            "mean": 617455.3424114162,
            "variance": null,
            "presence": null,
            "ignore_metric": false,
            "removal_reason": null,
            "was_log_transformed": false,
            "low_variance_detected": false,
            "final_weight": 0.125,
            "std": 582274.9713606192,
            "max": 2233117.31609976,
            "min": 233079.4319304817,
            "mean_normalized": 0.19218431486890866,
            "std_normalized": 0.2911319710338731,
            "max_normalized": 1.0,
            "min_normalized": 0.0
        },
        {
            "metric": "kl_divergence",
            "original_weight": 0.4,
            "normalized_weight": 0.125,
            "was_normalized": true,
            "was_inverted": false,
            "was_shared": false,
            "was_specific": false,
            "max_value": null,
            "min_value": null,
            "std_dev": null,
            "mean": -338376.2905575011,
            "variance": null,
            "presence": null,
            "ignore_metric": false,
            "removal_reason": null,
            "was_log_transformed": false,
            "low_variance_detected": false,
            "final_weight": 0.125,
            "std": NaN,
            "max": -338376.2905575011,
            "min": -338376.2905575011,
            "mean_normalized": 0.0,
            "std_normalized": NaN,
            "max_normalized": 0.0,
            "min_normalized": 0.0
        },
        {
            "metric": "prominence_min_diff",
            "original_weight": 0.3,
            "normalized_weight": 0.04347826086956521,
            "was_normalized": true,
            "was_inverted": false,
            "was_shared": false,
            "was_specific": false,
            "max_value": null,
            "min_value": null,
            "std_dev": null,
            "mean": 13243.361328004965,
            "variance": null,
            "presence": null,
            "ignore_metric": false,
            "removal_reason": null,
            "was_log_transformed": false,
            "low_variance_detected": false,
            "final_weight": 0.04347826086956521,
            "std": 17642.554919500653,
            "max": 58267.08960899949,
            "min": 2913.3025941865044,
            "mean_normalized": 0.18661882575539193,
            "std_normalized": 0.3187235394532158,
            "max_normalized": 1.0,
            "min_normalized": 0.0
        },
        {
            "metric": "positive_amplitudes_dtw",
            "original_weight": 0.35,
            "normalized_weight": 0.04347826086956521,
            "was_normalized": true,
            "was_inverted": false,
            "was_shared": false,
            "was_specific": false,
            "max_value": null,
            "min_value": null,
            "std_dev": null,
            "mean": 15943091.7602403,
            "variance": null,
            "presence": null,
            "ignore_metric": false,
            "removal_reason": null,
            "was_log_transformed": false,
            "low_variance_detected": false,
            "final_weight": 0.04347826086956521,
            "std": 6251106.229575737,
            "max": 25227585.602282427,
            "min": 7099906.750805811,
            "mean_normalized": 0.48782776227934743,
            "std_normalized": 0.3448376530052299,
            "max_normalized": 1.0,
            "min_normalized": 0.0
        },
        {
            "metric": "positive_amplitudes_euclidean",
            "original_weight": 0.35,
            "normalized_weight": 0.04347826086956521,
            "was_normalized": true,
            "was_inverted": false,
            "was_shared": false,
            "was_specific": false,
            "max_value": null,
            "min_value": null,
            "std_dev": null,
            "mean": 6293830.774925933,
            "variance": null,
            "presence": null,
            "ignore_metric": false,
            "removal_reason": null,
            "was_log_transformed": false,
            "low_variance_detected": false,
            "final_weight": 0.04347826086956521,
            "std": 4216820.551229715,
            "max": 15974117.616491666,
            "min": 2681162.492741108,
            "mean_normalized": 0.2717731496535379,
            "std_normalized": 0.3172222061966877,
            "max_normalized": 1.0,
            "min_normalized": 0.0
        },
        {
            "metric": "positive_amplitudes_wasserstein",
            "original_weight": 0.35,
            "normalized_weight": 0.04347826086956521,
            "was_normalized": true,
            "was_inverted": false,
            "was_shared": false,
            "was_specific": false,
            "max_value": null,
            "min_value": null,
            "std_dev": null,
            "mean": 206694.3999648547,
            "variance": null,
            "presence": null,
            "ignore_metric": false,
            "removal_reason": null,
            "was_log_transformed": false,
            "low_variance_detected": false,
            "final_weight": 0.04347826086956521,
            "std": 74823.43416710557,
            "max": 313889.5240531812,
            "min": 99327.24984437352,
            "mean_normalized": 0.5004008766983596,
            "std_normalized": 0.348725955869991,
            "max_normalized": 1.0,
            "min_normalized": 0.0
        },
        {
            "metric": "avg_prominence_diff",
            "original_weight": 0.3,
            "normalized_weight": 0.04347826086956521,
            "was_normalized": true,
            "was_inverted": false,
            "was_shared": false,
            "was_specific": false,
            "max_value": null,
            "min_value": null,
            "std_dev": null,
            "mean": 45438.45484719527,
            "variance": null,
            "presence": null,
            "ignore_metric": false,
            "removal_reason": null,
            "was_log_transformed": false,
            "low_variance_detected": false,
            "final_weight": 0.04347826086956521,
            "std": 22565.604834046022,
            "max": 91063.88644467184,
            "min": 24338.0460068482,
            "mean_normalized": 0.31622544882006876,
            "std_normalized": 0.33818389826161965,
            "max_normalized": 0.9999999999999999,
            "min_normalized": 0.0
        },
        {
            "metric": "relative_prominences_avg_diff",
            "original_weight": 0.3,
            "normalized_weight": 0.04347826086956521,
            "was_normalized": true,
            "was_inverted": false,
            "was_shared": false,
            "was_specific": false,
            "max_value": null,
            "min_value": null,
            "std_dev": null,
            "mean": 45438.45484719527,
            "variance": null,
            "presence": null,
            "ignore_metric": false,
            "removal_reason": null,
            "was_log_transformed": false,
            "low_variance_detected": false,
            "final_weight": 0.04347826086956521,
            "std": 22565.604834046022,
            "max": 91063.88644467184,
            "min": 24338.0460068482,
            "mean_normalized": 0.31622544882006876,
            "std_normalized": 0.33818389826161965,
            "max_normalized": 0.9999999999999999,
            "min_normalized": 0.0
        },
        {
            "metric": "relative_prominences_wasserstein",
            "original_weight": 0.3,
            "normalized_weight": 0.04347826086956521,
            "was_normalized": true,
            "was_inverted": false,
            "was_shared": false,
            "was_specific": false,
            "max_value": null,
            "min_value": null,
            "std_dev": null,
            "mean": 45438.45484719528,
            "variance": null,
            "presence": null,
            "ignore_metric": false,
            "removal_reason": null,
            "was_log_transformed": false,
            "low_variance_detected": false,
            "final_weight": 0.04347826086956521,
            "std": 22565.604834046022,
            "max": 91063.88644467184,
            "min": 24338.046006848203,
            "mean_normalized": 0.31622544882006876,
            "std_normalized": 0.33818389826161976,
            "max_normalized": 1.0,
            "min_normalized": 0.0
        },
        {
            "metric": "positive_frequencies_dtw",
            "original_weight": 0.35,
            "normalized_weight": null,
            "was_normalized": false,
            "was_inverted": false,
            "was_shared": false,
            "was_specific": false,
            "max_value": null,
            "min_value": null,
            "std_dev": null,
            "mean": 0.0,
            "variance": null,
            "presence": null,
            "ignore_metric": true,
            "removal_reason": "Low variance (std: 0.000000, mean: 0.000000)",
            "was_log_transformed": false,
            "low_variance_detected": true,
            "std": 0.0,
            "max": 0.0,
            "min": 0.0
        },
        {
            "metric": "positive_frequencies_euclidean",
            "original_weight": 0.35,
            "normalized_weight": null,
            "was_normalized": false,
            "was_inverted": false,
            "was_shared": false,
            "was_specific": false,
            "max_value": null,
            "min_value": null,
            "std_dev": null,
            "mean": 0.0,
            "variance": null,
            "presence": null,
            "ignore_metric": true,
            "removal_reason": "Low variance (std: 0.000000, mean: 0.000000)",
            "was_log_transformed": false,
            "low_variance_detected": true,
            "std": 0.0,
            "max": 0.0,
            "min": 0.0
        },
        {
            "metric": "positive_frequencies_wasserstein",
            "original_weight": 0.35,
            "normalized_weight": null,
            "was_normalized": false,
            "was_inverted": false,
            "was_shared": false,
            "was_specific": false,
            "max_value": null,
            "min_value": null,
            "std_dev": null,
            "mean": 0.0,
            "variance": null,
            "presence": null,
            "ignore_metric": true,
            "removal_reason": "Low variance (std: 0.000000, mean: 0.000000)",
            "was_log_transformed": false,
            "low_variance_detected": true,
            "std": 0.0,
            "max": 0.0,
            "min": 0.0
        },
        {
            "metric": "spectral_centroid_diff",
            "original_weight": 0.6,
            "normalized_weight": 0.04347826086956521,
            "was_normalized": true,
            "was_inverted": false,
            "was_shared": false,
            "was_specific": false,
            "max_value": null,
            "min_value": null,
            "std_dev": null,
            "mean": 0.09457768917535175,
            "variance": null,
            "presence": null,
            "ignore_metric": false,
            "removal_reason": null,
            "was_log_transformed": false,
            "low_variance_detected": false,
            "final_weight": 0.04347826086956521,
            "std": 0.037134695892067214,
            "max": 0.14144603142951065,
            "min": 0.04363297233757049,
            "mean_normalized": 0.520837578445383,
            "std_normalized": 0.37964967292518853,
            "max_normalized": 1.0,
            "min_normalized": 0.0
        },
        {
            "metric": "spectral_magnitude_diff",
            "original_weight": 0.6,
            "normalized_weight": 0.04347826086956521,
            "was_normalized": true,
            "was_inverted": false,
            "was_shared": false,
            "was_specific": false,
            "max_value": null,
            "min_value": null,
            "std_dev": null,
            "mean": 14909181.724341903,
            "variance": null,
            "presence": null,
            "ignore_metric": false,
            "removal_reason": null,
            "was_log_transformed": false,
            "low_variance_detected": false,
            "final_weight": 0.04347826086956521,
            "std": 7635463.999467776,
            "max": 25111161.924254492,
            "min": 271849.2687236059,
            "mean_normalized": 0.5892808975275348,
            "std_normalized": 0.30739433515555076,
            "max_normalized": 1.0,
            "min_normalized": 0.0
        },
        {
            "metric": "dynamic_cutoff_diff",
            "original_weight": 0.5,
            "normalized_weight": 0.04347826086956521,
            "was_normalized": true,
            "was_inverted": false,
            "was_shared": false,
            "was_specific": false,
            "max_value": null,
            "min_value": null,
            "std_dev": null,
            "mean": 9915.756783039085,
            "variance": null,
            "presence": null,
            "ignore_metric": false,
            "removal_reason": null,
            "was_log_transformed": false,
            "low_variance_detected": false,
            "final_weight": 0.04347826086956521,
            "std": 18430.571985271923,
            "max": 45165.29524441565,
            "min": 37.9,
            "mean_normalized": 0.2188882546741147,
            "std_normalized": 0.40841204960866073,
            "max_normalized": 1.0,
            "min_normalized": 0.0
        },
        {
            "metric": "relative_prominences_total_diff",
            "original_weight": 0.5,
            "normalized_weight": 0.04347826086956521,
            "was_normalized": true,
            "was_inverted": false,
            "was_shared": false,
            "was_specific": false,
            "max_value": null,
            "min_value": null,
            "std_dev": null,
            "mean": 117729.32691742663,
            "variance": null,
            "presence": null,
            "ignore_metric": false,
            "removal_reason": null,
            "was_log_transformed": false,
            "low_variance_detected": false,
            "final_weight": 0.04347826086956521,
            "std": 44871.80016876927,
            "max": 172415.7294110828,
            "min": 18442.16106707239,
            "mean_normalized": 0.6448325314415337,
            "std_normalized": 0.29142534430660144,
            "max_normalized": 1.0,
            "min_normalized": 0.0
        },
        {
            "metric": "prominence_max_diff",
            "original_weight": 0.5,
            "normalized_weight": 0.04347826086956521,
            "was_normalized": true,
            "was_inverted": false,
            "was_shared": false,
            "was_specific": false,
            "max_value": null,
            "min_value": null,
            "std_dev": null,
            "mean": 88161.22186808685,
            "variance": null,
            "presence": null,
            "ignore_metric": false,
            "removal_reason": null,
            "was_log_transformed": false,
            "low_variance_detected": false,
            "final_weight": 0.04347826086956521,
            "std": 33203.34141869641,
            "max": 141895.76254511456,
            "min": 28216.16106707239,
            "mean_normalized": 0.527315895038506,
            "std_normalized": 0.2920782707450801,
            "max_normalized": 1.0,
            "min_normalized": 0.0
        },
        {
            "metric": "amplitude_max_diff",
            "original_weight": 0.5,
            "normalized_weight": 0.04347826086956521,
            "was_normalized": true,
            "was_inverted": false,
            "was_shared": false,
            "was_specific": false,
            "max_value": null,
            "min_value": null,
            "std_dev": null,
            "mean": 1673744.5034111196,
            "variance": null,
            "presence": null,
            "ignore_metric": false,
            "removal_reason": null,
            "was_log_transformed": false,
            "low_variance_detected": false,
            "final_weight": 0.04347826086956521,
            "std": 635825.7839597978,
            "max": 2466499.825368644,
            "min": 369290.9665689794,
            "mean_normalized": 0.62199505374431,
            "std_normalized": 0.30317714007927277,
            "max_normalized": 1.0,
            "min_normalized": 0.0
        },
        {
            "metric": "frequency_max_diff",
            "original_weight": 0.5,
            "normalized_weight": null,
            "was_normalized": false,
            "was_inverted": false,
            "was_shared": false,
            "was_specific": false,
            "max_value": null,
            "min_value": null,
            "std_dev": null,
            "mean": 0.0,
            "variance": null,
            "presence": null,
            "ignore_metric": true,
            "removal_reason": "Low variance (std: 0.000000, mean: 0.000000)",
            "was_log_transformed": false,
            "low_variance_detected": true,
            "std": 0.0,
            "max": 0.0,
            "min": 0.0
        },
        {
            "metric": "spectral_bandwidth_diff",
            "original_weight": 0.5,
            "normalized_weight": 0.04347826086956521,
            "was_normalized": true,
            "was_inverted": false,
            "was_shared": false,
            "was_specific": false,
            "max_value": null,
            "min_value": null,
            "std_dev": null,
            "mean": 0.05758339696147089,
            "variance": null,
            "presence": null,
            "ignore_metric": false,
            "removal_reason": null,
            "was_log_transformed": false,
            "low_variance_detected": false,
            "final_weight": 0.04347826086956521,
            "std": 0.0316682852821145,
            "max": 0.10438820628847902,
            "min": 0.020263598947330486,
            "mean_normalized": 0.4436252268352148,
            "std_normalized": 0.37644496994429766,
            "max_normalized": 1.0,
            "min_normalized": 0.0
        },
        {
            "metric": "num_fft_peaks_diff",
            "original_weight": 0.4,
            "normalized_weight": 0.04347826086956521,
            "was_normalized": true,
            "was_inverted": false,
            "was_shared": false,
            "was_specific": false,
            "max_value": null,
            "min_value": null,
            "std_dev": null,
            "mean": 0.5555555555555556,
            "variance": null,
            "presence": null,
            "ignore_metric": false,
            "removal_reason": null,
            "was_log_transformed": false,
            "low_variance_detected": false,
            "final_weight": 0.04347826086956521,
            "std": 0.5270462766947299,
            "max": 1.0,
            "min": 0.0,
            "mean_normalized": 0.5555555555555556,
            "std_normalized": 0.5270462766947299,
            "max_normalized": 1.0,
            "min_normalized": 0.0
        },
        {
            "metric": "relative_num_peaks_diff",
            "original_weight": 0.4,
            "normalized_weight": 0.04347826086956521,
            "was_normalized": true,
            "was_inverted": false,
            "was_shared": false,
            "was_specific": false,
            "max_value": null,
            "min_value": null,
            "std_dev": null,
            "mean": 19.9,
            "variance": null,
            "presence": null,
            "ignore_metric": false,
            "removal_reason": null,
            "was_log_transformed": false,
            "low_variance_detected": false,
            "final_weight": 0.04347826086956521,
            "std": 1.449137674618944,
            "max": 22.0,
            "min": 17.0,
            "mean_normalized": 0.5800000000000001,
            "std_normalized": 0.28982753492378877,
            "max_normalized": 1.0,
            "min_normalized": 0.0
        },
        {
            "metric": "dominant_frequency_diff",
            "original_weight": 0.5,
            "normalized_weight": 0.04347826086956521,
            "was_normalized": true,
            "was_inverted": false,
            "was_shared": false,
            "was_specific": false,
            "max_value": null,
            "min_value": null,
            "std_dev": null,
            "mean": 0.004166666666666667,
            "variance": null,
            "presence": null,
            "ignore_metric": false,
            "removal_reason": null,
            "was_log_transformed": false,
            "low_variance_detected": false,
            "final_weight": 0.04347826086956521,
            "std": 0.008267972847076846,
            "max": 0.01875,
            "min": 0.0,
            "mean_normalized": 0.2222222222222222,
            "std_normalized": 0.44095855184409843,
            "max_normalized": 1.0,
            "min_normalized": 0.0
        },
        {
            "metric": "max_autocorrelation_diff",
            "original_weight": 0.5,
            "normalized_weight": 0.04347826086956521,
            "was_normalized": true,
            "was_inverted": false,
            "was_shared": false,
            "was_specific": false,
            "max_value": null,
            "min_value": null,
            "std_dev": null,
            "mean": 576720012623.1394,
            "variance": null,
            "presence": null,
            "ignore_metric": false,
            "removal_reason": null,
            "was_log_transformed": false,
            "low_variance_detected": false,
            "final_weight": 0.04347826086956521,
            "std": 617012316411.5128,
            "max": 1737323782129.1729,
            "min": 86489385558.30296,
            "mean_normalized": 0.2969593001473366,
            "std_normalized": 0.37375785099533737,
            "max_normalized": 1.0,
            "min_normalized": 0.0
        },
        {
            "metric": "relative_right_bases_global_alignment_score",
            "original_weight": 0.1,
            "normalized_weight": 0.04347826086956521,
            "was_normalized": true,
            "was_inverted": false,
            "was_shared": false,
            "was_specific": false,
            "max_value": null,
            "min_value": null,
            "std_dev": null,
            "mean": -17.4,
            "variance": null,
            "presence": null,
            "ignore_metric": false,
            "removal_reason": null,
            "was_log_transformed": false,
            "low_variance_detected": false,
            "final_weight": 0.04347826086956521,
            "std": 4.135214625627067,
            "max": -11.5,
            "min": -22.5,
            "mean_normalized": 0.46363636363636357,
            "std_normalized": 0.37592860232973335,
            "max_normalized": 1.0,
            "min_normalized": 0.0
        },
        {
            "metric": "relative_right_bases_array_alignment_score",
            "original_weight": 0.1,
            "normalized_weight": null,
            "was_normalized": false,
            "was_inverted": false,
            "was_shared": false,
            "was_specific": false,
            "max_value": null,
            "min_value": null,
            "std_dev": null,
            "mean": 0.0,
            "variance": null,
            "presence": null,
            "ignore_metric": true,
            "removal_reason": "Low variance (std: 0.000000, mean: 0.000000)",
            "was_log_transformed": false,
            "low_variance_detected": true,
            "std": 0.0,
            "max": 0.0,
            "min": 0.0
        },
        {
            "metric": "relative_left_bases_global_alignment_score",
            "original_weight": 0.1,
            "normalized_weight": 0.04347826086956521,
            "was_normalized": true,
            "was_inverted": false,
            "was_shared": false,
            "was_specific": false,
            "max_value": null,
            "min_value": null,
            "std_dev": null,
            "mean": -16.95,
            "variance": null,
            "presence": null,
            "ignore_metric": false,
            "removal_reason": null,
            "was_log_transformed": false,
            "low_variance_detected": false,
            "final_weight": 0.04347826086956521,
            "std": 5.101470376273884,
            "max": -7.0,
            "min": -22.5,
            "mean_normalized": 0.35806451612903223,
            "std_normalized": 0.329127121049928,
            "max_normalized": 1.0,
            "min_normalized": 0.0
        },
        {
            "metric": "relative_left_bases_array_alignment_score",
            "original_weight": 0.1,
            "normalized_weight": null,
            "was_normalized": false,
            "was_inverted": false,
            "was_shared": false,
            "was_specific": false,
            "max_value": null,
            "min_value": null,
            "std_dev": null,
            "mean": 0.0,
            "variance": null,
            "presence": null,
            "ignore_metric": true,
            "removal_reason": "Low variance (std: 0.000000, mean: 0.000000)",
            "was_log_transformed": false,
            "low_variance_detected": true,
            "std": 0.0,
            "max": 0.0,
            "min": 0.0
        },
        {
            "metric": "upper_envelope_diff",
            "original_weight": 0.2,
            "normalized_weight": 0.04347826086956521,
            "was_normalized": true,
            "was_inverted": false,
            "was_shared": false,
            "was_specific": false,
            "max_value": null,
            "min_value": null,
            "std_dev": null,
            "mean": 98329.04544965006,
            "variance": null,
            "presence": null,
            "ignore_metric": false,
            "removal_reason": null,
            "was_log_transformed": false,
            "low_variance_detected": false,
            "final_weight": 0.04347826086956521,
            "std": 47721.69023493797,
            "max": 194981.36574944048,
            "min": 46667.15126018939,
            "mean_normalized": 0.34832732902485763,
            "std_normalized": 0.32176073210027045,
            "max_normalized": 1.0,
            "min_normalized": 0.0
        },
        {
            "metric": "lower_envelope_diff",
            "original_weight": 0.2,
            "normalized_weight": 0.04347826086956521,
            "was_normalized": true,
            "was_inverted": false,
            "was_shared": false,
            "was_specific": false,
            "max_value": null,
            "min_value": null,
            "std_dev": null,
            "mean": 98329.04544965006,
            "variance": null,
            "presence": null,
            "ignore_metric": false,
            "removal_reason": null,
            "was_log_transformed": false,
            "low_variance_detected": false,
            "final_weight": 0.04347826086956521,
            "std": 47721.69023493797,
            "max": 194981.36574944048,
            "min": 46667.15126018939,
            "mean_normalized": 0.34832732902485763,
            "std_normalized": 0.32176073210027045,
            "max_normalized": 1.0,
            "min_normalized": 0.0
        },
        {
            "metric": "relative_peaks_array_alignment_score",
            "original_weight": 0.2,
            "normalized_weight": null,
            "was_normalized": false,
            "was_inverted": false,
            "was_shared": false,
            "was_specific": false,
            "max_value": null,
            "min_value": null,
            "std_dev": null,
            "mean": 0.0,
            "variance": null,
            "presence": null,
            "ignore_metric": true,
            "removal_reason": "Low variance (std: 0.000000, mean: 0.000000)",
            "was_log_transformed": false,
            "low_variance_detected": true,
            "std": 0.0,
            "max": 0.0,
            "min": 0.0
        },
        {
            "metric": "relative_peaks_global_alignment_score",
            "original_weight": 0.2,
            "normalized_weight": 0.04347826086956521,
            "was_normalized": true,
            "was_inverted": false,
            "was_shared": false,
            "was_specific": false,
            "max_value": null,
            "min_value": null,
            "std_dev": null,
            "mean": -19.2,
            "variance": null,
            "presence": null,
            "ignore_metric": false,
            "removal_reason": null,
            "was_log_transformed": false,
            "low_variance_detected": false,
            "final_weight": 0.04347826086956521,
            "std": 3.72827037646145,
            "max": -11.5,
            "min": -22.5,
            "mean_normalized": 0.3,
            "std_normalized": 0.3389336705874045,
            "max_normalized": 0.9999999999999999,
            "min_normalized": 0.0
        }
    ],
    "penalty_weight": 0.05,
    "reconstruction_normalized_weighted_max": 1.0,
    "reconstruction_normalized_weighted_min": 0.2654995713472679,
    "reconstruction_normalized_weighted_mean": 0.5028592303454121,
    "reconstruction_normalized_weighted_std": 0.23652851068950637,
    "signal_normalized_weighted_max": 1.0,
    "signal_normalized_weighted_min": 0.7613590427254074,
    "signal_normalized_weighted_mean": 0.9088336843279473,
    "signal_normalized_weighted_std": 0.08624361353507295,
    "ranking_columns": [
        "reconstruction_normalized_weighted_rank",
        "reconstruction_normalized_dynamically_weighted_rank",
        "signal_normalized_weighted_rank",
        "signal_normalized_dynamically_weighted_rank"
    ],
    "selected_family_rank_stability_column": "family_informed_rank",
    "selected_family_rank_stability_column_correlation": 0.9975055850078428
}